keymouse/__init__.py
keymouse/keymouse.py
keymouse-0.0.6.dist-info/LICENCE.txt
keymouse-0.0.6.dist-info/METADATA
keymouse-0.0.6.dist-info/WHEEL
keymouse-0.0.6.dist-info/top_level.txt
keymouse-0.0.6.dist-info/RECORD
