Metadata-Version: 2.1
Name: keymouse
Version: 0.0.6
Summary: Python module to work with keyboard and mouse
Author-email: Roman Smolnyk <poma23324@gmail.com>
Project-URL: Homepage, https://gitlab.com/roman-smolnyk/keymouse
Keywords: mouse,keyboard,automation
Classifier: Programming Language :: Python :: 3
Classifier: License :: OSI Approved :: MIT License
Classifier: Operating System :: OS Independent
Requires-Python: >=3.8
License-File: LICENCE.txt
Requires-Dist: pynput
Requires-Dist: pyautogui
Requires-Dist: pylayout
